ics2todoist.py
ics2todoist-0.1.0.dist-info/LICENSE.txt
ics2todoist-0.1.0.dist-info/METADATA
ics2todoist-0.1.0.dist-info/WHEEL
ics2todoist-0.1.0.dist-info/entry_points.txt
ics2todoist-0.1.0.dist-info/top_level.txt
ics2todoist-0.1.0.dist-info/zip-safe
ics2todoist-0.1.0.dist-info/RECORD
