Metadata-Version: 2.1
Name: ics2todoist
Version: 0.1.0
Summary: Convert iCalendar tasks to CSV for import into Todoist.
Home-page: https://gitlab.com/kevinoid/ics2todoist
Author: Kevin Locke
Author-email: kevin@kevinlocke.name
License: MIT License
Project-URL: Documentation, https://ics2todoist.readthedocs.io/
Project-URL: Source, https://gitlab.com/kevinoid/ics2todoist
Project-URL: Tracker, https://gitlab.com/kevinoid/ics2todoist/-/issues
Keywords: converter csv ical icalendar todoist
Classifier: Development Status :: 4 - Beta
Classifier: Intended Audience :: Information Technology
Classifier: License :: OSI Approved :: MIT License
Classifier: Operating System :: OS Independent
Classifier: Programming Language :: Python
Classifier: Programming Language :: Python :: 3
Classifier: Programming Language :: Python :: 3.7
Classifier: Programming Language :: Python :: 3.8
Classifier: Programming Language :: Python :: 3.9
Classifier: Programming Language :: Python :: 3.10
Classifier: Programming Language :: Python :: Implementation :: CPython
Classifier: Programming Language :: Python :: Implementation :: PyPy
Classifier: Topic :: Office/Business :: Groupware
Classifier: Topic :: Office/Business :: Scheduling
Classifier: Topic :: Text Processing
Classifier: Topic :: Utilities
Requires-Python: >=3.7
License-File: LICENSE.txt
Requires-Dist: html2text (==2020.1.16)
Requires-Dist: icalendar (~=4.0)
Provides-Extra: argcomplete
Requires-Dist: argcomplete (~=2.0) ; extra == 'argcomplete'
